korch/__init__.py
korch/_nbdev.py
korch/core.py
korch-0.0.2.dist-info/LICENSE
korch-0.0.2.dist-info/METADATA
korch-0.0.2.dist-info/WHEEL
korch-0.0.2.dist-info/top_level.txt
korch-0.0.2.dist-info/RECORD
