Metadata-Version: 2.1
Name: korch
Version: 0.0.2
Summary: Simple tools to provide a Keras-like interface to PyTorch.
Home-page: https://github.com/Jorgvt/korch/tree/master/
Author: Jorge Vila Tomás
Author-email: jorge.vila-tomas@uv.es
License: Apache Software License 2.0
Keywords: pytorch keras python nbdev
Platform: UNKNOWN
Classifier: Development Status :: 3 - Alpha
Classifier: Intended Audience :: Developers
Classifier: Natural Language :: English
Classifier: Programming Language :: Python :: 3.6
Classifier: Programming Language :: Python :: 3.7
Classifier: Programming Language :: Python :: 3.8
Classifier: Programming Language :: Python :: 3.9
Classifier: Programming Language :: Python :: 3.10
Classifier: License :: OSI Approved :: Apache Software License
Requires-Python: >=3.6
License-File: LICENSE
Requires-Dist: pip
Requires-Dist: packaging
Requires-Dist: torchvision
Requires-Dist: tqdm
Requires-Dist: torchmetrics
Requires-Dist: torch
Provides-Extra: dev
